README.md
setup.cfg
setup.py
distributions/Binomialdistribution.py
distributions/Gaussiandistribution.py
distributions/Generaldistribution.py
distributions/__init__.py
jxtr_distributions.egg-info/PKG-INFO
jxtr_distributions.egg-info/SOURCES.txt
jxtr_distributions.egg-info/dependency_links.txt
jxtr_distributions.egg-info/not-zip-safe
jxtr_distributions.egg-info/top_level.txt